pydra/tasks/freesurfer/__init__.py
pydra/tasks/freesurfer/_version.py
pydra/tasks/freesurfer/latest.py
pydra/tasks/freesurfer/auto/__init__.py
pydra/tasks/freesurfer/auto/_post_release.py
pydra/tasks/freesurfer/auto/longitudinal/__init__.py
pydra/tasks/freesurfer/auto/longitudinal/fuse_segmentations.py
pydra/tasks/freesurfer/auto/longitudinal/robust_template.py
pydra/tasks/freesurfer/auto/longitudinal/tests/conftest.py
pydra/tasks/freesurfer/auto/longitudinal/tests/test_fusesegmentations.py
pydra/tasks/freesurfer/auto/longitudinal/tests/test_robusttemplate.py
pydra/tasks/freesurfer/auto/model/__init__.py
pydra/tasks/freesurfer/auto/model/binarize.py
pydra/tasks/freesurfer/auto/model/concatenate.py
pydra/tasks/freesurfer/auto/model/glm_fit.py
pydra/tasks/freesurfer/auto/model/label_2_annot.py
pydra/tasks/freesurfer/auto/model/label_2_label.py
pydra/tasks/freesurfer/auto/model/label_2_vol.py
pydra/tasks/freesurfer/auto/model/mris_preproc.py
pydra/tasks/freesurfer/auto/model/mris_preproc_recon_all.py
pydra/tasks/freesurfer/auto/model/ms__lda.py
pydra/tasks/freesurfer/auto/model/one_sample_t_test.py
pydra/tasks/freesurfer/auto/model/seg_stats.py
pydra/tasks/freesurfer/auto/model/seg_stats_recon_all.py
pydra/tasks/freesurfer/auto/model/spherical_average.py
pydra/tasks/freesurfer/auto/model/tests/conftest.py
pydra/tasks/freesurfer/auto/model/tests/test_binarize.py
pydra/tasks/freesurfer/auto/model/tests/test_concatenate.py
pydra/tasks/freesurfer/auto/model/tests/test_glmfit.py
pydra/tasks/freesurfer/auto/model/tests/test_label2annot.py
pydra/tasks/freesurfer/auto/model/tests/test_label2label.py
pydra/tasks/freesurfer/auto/model/tests/test_label2vol.py
pydra/tasks/freesurfer/auto/model/tests/test_mrispreproc.py
pydra/tasks/freesurfer/auto/model/tests/test_mrispreprocreconall.py
pydra/tasks/freesurfer/auto/model/tests/test_ms_lda.py
pydra/tasks/freesurfer/auto/model/tests/test_onesamplettest.py
pydra/tasks/freesurfer/auto/model/tests/test_segstats.py
pydra_freesurfer-0.1.1.dist-info/METADATA
pydra_freesurfer-0.1.1.dist-info/WHEEL
pydra_freesurfer-0.1.1.dist-info/licenses/LICENSE
pydra_freesurfer-0.1.1.dist-info/licenses/NOTICE
pydra_freesurfer-0.1.1.dist-info/RECORD
